smooth_operator/__init__.py
smooth_operator/__main__.py
smooth_operator/cli.py
smooth_operator/channels/__init__.py
smooth_operator/channels/base.py
smooth_operator/channels/gitlab.py
smooth_operator/channels/lando.py
smooth_operator/channels/terminus.py
smooth_operator/cli/__init__.py
smooth_operator/cli/commands/__init__.py
smooth_operator/cli/commands/extension_commands.py
smooth_operator/cli/commands/site_commands.py
smooth_operator/cli/commands/upstream_commands.py
smooth_operator/config/__init__.py
smooth_operator/config/settings.py
smooth_operator/core/__init__.py
smooth_operator/core/exceptions.py
smooth_operator/core/models.py
smooth_operator/core/mixins/__init__.py
smooth_operator/core/mixins/debug.py
smooth_operator/core/mixins/process.py
smooth_operator/operations/__init__.py
smooth_operator/operations/executor/graph.py
smooth_operator/operations/stages/manager.py
smooth_operator/operations/updater/__init__.py
smooth_operator/operations/updater/batch.py
smooth_operator/operations/updater/manifest.py
smooth_operator/operations/updater/runner.py
smooth_operator/operations/updater/task.py
smooth_operator/utils/__init__.py
smooth_operator/utils/async_utils.py
smooth_operator/utils/filtering.py
smooth_operator/utils/logging.py
smooth_operator/utils/progress.py
smooth_operator-0.1.0.dist-info/METADATA
smooth_operator-0.1.0.dist-info/WHEEL
smooth_operator-0.1.0.dist-info/entry_points.txt
smooth_operator-0.1.0.dist-info/top_level.txt
smooth_operator-0.1.0.dist-info/RECORD
