Metadata-Version: 2.4
Name: smooth_operator
Version: 0.1.0
Summary: CLI client for managing Drupal sites across multiple operation channels
Author-email: Your Name <your.email@example.com>
License: Proprietary
Classifier: Development Status :: 4 - Beta
Classifier: Intended Audience :: Developers
Classifier: Intended Audience :: System Administrators
Classifier: Programming Language :: Python :: 3
Classifier: Programming Language :: Python :: 3.8
Classifier: Programming Language :: Python :: 3.9
Classifier: Programming Language :: Python :: 3.10
Classifier: Programming Language :: Python :: 3.11
Classifier: Topic :: Software Development :: Libraries :: Python Modules
Classifier: Topic :: System :: Systems Administration
Requires-Python: >=3.8
Requires-Dist: click>=8.0.0
Requires-Dist: rich>=10.0.0
Requires-Dist: structlog>=21.1.0
Requires-Dist: pyyaml>=6.0
Requires-Dist: httpx>=0.20.0
Requires-Dist: jsonpickle>=2.0.0
Requires-Dist: typer>=0.4.0
Requires-Dist: pydantic>=2.0
Provides-Extra: dev
Requires-Dist: pytest>=6.0.0; extra == "dev"
Requires-Dist: black>=21.5b2; extra == "dev"
Requires-Dist: flake8>=3.9.2; extra == "dev"
Requires-Dist: mypy>=0.812; extra == "dev"
Provides-Extra: standalone
Requires-Dist: pyinstaller>=5.0; extra == "standalone"
